{
  "project_info": {
    "project_number": "320703464240",
    "project_id": "mumblit-fe888",
    "storage_bucket": "mumblit-fe888.appspot.com"
  },
  "client": [
    {
      "client_info": {
        "mobilesdk_app_id": "1:320703464240:android:ea7796a615edf97ab37ef5",
        "android_client_info": {
          "package_name": "com.mumblitsoc.app"
        }
      },
      "oauth_client": [
        {
          "client_id": "320703464240-q9l462vtntsli8qlcr6p3pnagsh3r2ed.apps.googleusercontent.com",
          "client_type": 1,
          "android_info": {
            "package_name": "com.mumblitsoc.app",
            "certificate_hash": "f1f379619026c2e37782072fb2d3a2e23d921460"
          }
        },
        {
          "client_id": "320703464240-kf0jioq9ikpe48eoafi3e4e2upjtcmbe.apps.googleusercontent.com",
          "client_type": 3
        }
      ],
      "api_key": [
        {
          "current_key": "AIzaSyAGboPP5n_oJTH3wxtSb_EHDZZY-aGLe_M"
        }
      ],
      "services": {
        "appinvite_service": {
          "other_platform_oauth_client": [
            {
              "client_id": "320703464240-kf0jioq9ikpe48eoafi3e4e2upjtcmbe.apps.googleusercontent.com",
              "client_type": 3
            }
          ]
        }
      }
    }
  ],
  "configuration_version": "1"
}